{
  "OnInitSequece": [],
  "OnStartSequece": [
    {
      "IsLoop": true,
      "TaskList": [
        {
          "$type": "RPG.GameCore.WaitGroupEvent",
          "EventName": {
            "Value": "EnterArea_G62"
          },
          "OnEvent": [
            {
              "$type": "RPG.GameCore.SetMissionAudioState",
              "SetBGMEmotionState": true,
              "BGMEmotionStateName": "State_Esilence",
              "TaskEnabled": true,
              "IsClientOnly": true
            },
            {
              "$type": "RPG.GameCore.TriggerPerformance",
              "ValueSource": {},
              "PerformanceType": "D",
              "PerformanceID": 104041121,
              "MaskConfig": {
                "StartBlack": "Full",
                "EndBlack": "NoPost",
                "MaskColor": "Black"
              },
              "TaskEnabled": true,
              "IsClientOnly": true
            },
            {
              "$type": "RPG.GameCore.SetMissionAudioState",
              "SetBGMEmotionState": true,
              "BGMEmotionStateName": "State_Bgm_E1",
              "SetDefaultBGMEmotionState": true,
              "TaskEnabled": true,
              "IsClientOnly": true
            },
            {
              "$type": "RPG.GameCore.TriggerPerformance",
              "ValueSource": {},
              "PerformanceType": "D",
              "PerformanceID": 104041123,
              "MaskConfig": {
                "StartBlack": "NoPre",
                "EndBlack": "Full",
                "MaskColor": "Black"
              },
              "TaskEnabled": true,
              "IsClientOnly": true
            },
            {
              "$type": "RPG.GameCore.ClientFinishMission",
              "SubmissionID": 104041104,
              "TaskEnabled": true,
              "IsClientOnly": true
            }
          ],
          "IsLoop": true,
          "TaskEnabled": true,
          "IsClientOnly": true
        }
      ]
    },
    {
      "TaskList": [
        {
          "$type": "RPG.GameCore.AdvSetupCustomTaskTrigger",
          "TargetType": {
            "$type": "RPG.GameCore.GroupFetchLocalTarget",
            "TargetType": "Prop",
            "Targets": [
              300001
            ]
          },
          "TriggerName": "MissionTrigger",
          "OnEnter": [
            {
              "$type": "RPG.GameCore.TriggerGroupEvent",
              "EventName": {
                "Value": "EnterArea_G62"
              },
              "TaskEnabled": true,
              "IsClientOnly": true
            }
          ],
          "DisableAfterTriggered": true,
          "TaskEnabled": true,
          "IsClientOnly": true
        }
      ]
    }
  ],
  "Type": "Group"
}