{
  "OnInitSequece": [
    {
      "TaskList": []
    }
  ],
  "OnStartSequece": [
    {
      "TaskList": [
        {
          "$type": "RPG.GameCore.PredicateTaskList",
          "Predicate": {
            "$type": "RPG.GameCore.ByHeroGender",
            "Gender": "GENDER_WOMAN",
            "TaskEnabled": true,
            "IsClientOnly": true
          },
          "SuccessTaskList": [
            {
              "$type": "RPG.GameCore.AdvCreateGroupEntity",
              "InstanceIDList": [
                400001,
                400003,
                400005,
                400007
              ],
              "TaskEnabled": true,
              "IsClientOnly": true
            }
          ],
          "FailedTaskList": [
            {
              "$type": "RPG.GameCore.AdvCreateGroupEntity",
              "InstanceIDList": [
                400002,
                400004,
                400006,
                400008
              ],
              "TaskEnabled": true,
              "IsClientOnly": true
            }
          ],
          "TaskEnabled": true
        }
      ]
    }
  ],
  "Type": "Group"
}