{
  "OnInitSequece": [],
  "OnStartSequece": [
    {
      "TaskList": [
        {
          "$type": "RPG.GameCore.AdvOnButtonPressed",
          "ButtonName": "Interaction_G29",
          "OnPressedCallback": [
            {
              "$type": "RPG.GameCore.TriggerPerformance",
              "ValueSource": {},
              "PerformanceType": "E",
              "PerformanceID": 104060508,
              "MaskConfig": {
                "MaskColor": "Black"
              },
              "TaskEnabled": true,
              "IsClientOnly": true
            }
          ],
          "TaskEnabled": true,
          "IsClientOnly": true
        }
      ]
    },
    {
      "TaskList": [
        {
          "$type": "RPG.GameCore.AdvSetupButtonListTrigger",
          "TargetType": {
            "$type": "RPG.GameCore.GroupFetchLocalTarget",
            "TargetType": "Prop",
            "Targets": [
              300001
            ]
          },
          "TriggerName": "MissionTrigger",
          "ButtonsByName": [],
          "ButtonConfigs": [
            {
              "ID": "Interaction_G29",
              "IconType": {
                "JsonValueStr": "ChatIcon"
              },
              "ButtonText": {
                "Value": "PropInteractTitle_5"
              },
              "ShowPriority": "Default"
            }
          ],
          "InteractAngleRange": 180.0,
          "OwnerForwardAngleRange": 90.0,
          "TaskEnabled": true,
          "IsClientOnly": true
        }
      ]
    },
    {
      "TaskList": [
        {
          "$type": "RPG.GameCore.AdvOnButtonPressed",
          "ButtonName": "Interaction_G29_2",
          "OnPressedCallback": [
            {
              "$type": "RPG.GameCore.TriggerPerformance",
              "ValueSource": {},
              "PerformanceType": "E",
              "PerformanceID": 104060509,
              "MaskConfig": {
                "MaskColor": "Black"
              },
              "TaskEnabled": true,
              "IsClientOnly": true
            }
          ],
          "TaskEnabled": true,
          "IsClientOnly": true
        }
      ]
    },
    {
      "TaskList": [
        {
          "$type": "RPG.GameCore.AdvSetupButtonListTrigger",
          "TargetType": {
            "$type": "RPG.GameCore.GroupFetchLocalTarget",
            "TargetType": "Prop",
            "Targets": [
              300002
            ]
          },
          "TriggerName": "MissionTrigger",
          "ButtonsByName": [],
          "ButtonConfigs": [
            {
              "ID": "Interaction_G29_2",
              "IconType": {
                "JsonValueStr": "ChatIcon"
              },
              "ButtonText": {
                "Value": "PropInteractTitle_5"
              },
              "ShowPriority": "Default"
            }
          ],
          "InteractAngleRange": 180.0,
          "OwnerForwardAngleRange": 90.0,
          "TaskEnabled": true,
          "IsClientOnly": true
        }
      ]
    },
    {
      "TaskList": [
        {
          "$type": "RPG.GameCore.AdvOnButtonPressed",
          "ButtonName": "Interaction_G29_3",
          "OnPressedCallback": [
            {
              "$type": "RPG.GameCore.TriggerPerformance",
              "ValueSource": {},
              "PerformanceType": "E",
              "PerformanceID": 104060510,
              "MaskConfig": {
                "MaskColor": "Black"
              },
              "TaskEnabled": true,
              "IsClientOnly": true
            }
          ],
          "TaskEnabled": true,
          "IsClientOnly": true
        }
      ]
    },
    {
      "TaskList": [
        {
          "$type": "RPG.GameCore.AdvSetupButtonListTrigger",
          "TargetType": {
            "$type": "RPG.GameCore.GroupFetchLocalTarget",
            "TargetType": "Prop",
            "Targets": [
              300003
            ]
          },
          "TriggerName": "MissionTrigger",
          "ButtonsByName": [],
          "ButtonConfigs": [
            {
              "ID": "Interaction_G29_3",
              "IconType": {
                "JsonValueStr": "ChatIcon"
              },
              "ButtonText": {
                "Value": "PropInteractTitle_5"
              },
              "ShowPriority": "Default"
            }
          ],
          "InteractAngleRange": 180.0,
          "OwnerForwardAngleRange": 90.0,
          "TaskEnabled": true,
          "IsClientOnly": true
        }
      ]
    }
  ],
  "Type": "Group",
  "EntityEventList": []
}