{
  "AbilityList": [
    {
      "Name": "MazeMonster_W2_Beast02_01_NormalAtk01",
      "TargetInfo": {
        "TargetType": "SkillPointEntity"
      },
      "OnStart": [
        {
          "$type": "RPG.GameCore.LookAt",
          "PerformerType": {
            "$type": "RPG.GameCore.TargetAlias",
            "Alias": "Caster"
          },
          "TargetType": "AbilityTargetEntity",
          "ToTargetRatio": 1.0,
          "Duration": 0.2,
          "TaskEnabled": true,
          "IsClientOnly": true
        },
        {
          "$type": "RPG.GameCore.AdventureTriggerAnimStateWithMove",
          "TargetType": {
            "$type": "RPG.GameCore.TargetAlias",
            "Alias": "Caster"
          },
          "AnimLogicState": "NormalAtk",
          "AnimStateName": "Attack",
          "TransitionDuration": 0.05,
          "StopWhenHitOthers": true,
          "MovingRangeList": [
            {
              "TargetType": {
                "$type": "RPG.GameCore.TargetAlias",
                "Alias": "AbilityTargetEntity"
              },
              "SteerNormalizedTimeStart": {
                "FixedValue": {
                  "RawValue": 42949673,
                  "Value": 0.01
                }
              },
              "SteerNormalizedTimeEnd": {
                "FixedValue": {
                  "RawValue": 1666447310,
                  "Value": 0.39
                }
              },
              "MaxSteerSpeed": {
                "FixedValue": {
                  "RawValue": 1288490188800,
                  "Value": 300.0
                }
              }
            }
          ],
          "TaskEnabled": true,
          "IsClientOnly": true
        },
        {
          "$type": "RPG.GameCore.WaitAnimState",
          "TargetType": {
            "$type": "RPG.GameCore.TargetAlias",
            "Alias": "Caster"
          },
          "AnimStateName": "Attack",
          "NormalizedTimeEnd": {
            "FixedValue": {
              "RawValue": 794568949,
              "Value": 0.18
            }
          },
          "TaskEnabled": true,
          "IsClientOnly": true
        },
        {
          "$type": "RPG.GameCore.TriggerEffect",
          "TargetType": {
            "$type": "RPG.GameCore.TargetAlias",
            "Alias": "Caster"
          },
          "EffectPath": "Effects/Eff_Prefab/Eff_Monster/Eff_W2_Beast02_01/Eff_Monster_W2_Beast02_01_MazeSkill01_Bullet_01_Lod0.prefab",
          "UniqueEffectName": "FireBall1",
          "AttachPoint": "Eff_HandL",
          "RotationOffset": {
            "x": 160.0,
            "z": -30.0,
            "normalized": {
              "x": 0.9828722,
              "z": -0.184288532,
              "magnitude": 1.0,
              "sqrMagnitude": 1.0
            },
            "magnitude": 162.788208,
            "sqrMagnitude": 26500.0
          },
          "Scale": {
            "x": -1.0,
            "y": -1.0,
            "z": -1.0,
            "normalized": {
              "x": -0.577350259,
              "y": -0.577350259,
              "z": -0.577350259,
              "normalized": {
                "x": -0.5773503,
                "y": -0.5773503,
                "z": -0.5773503,
                "magnitude": 1.00000012,
                "sqrMagnitude": 1.00000024
              },
              "magnitude": 0.99999994,
              "sqrMagnitude": 0.99999994
            },
            "magnitude": 1.73205078,
            "sqrMagnitude": 3.0
          },
          "IsNeedFadeIn": true,
          "ParamEntityUsage": "LookAt",
          "TowardMaxPitchAngle": 90.0,
          "MaxMutexCount": 1,
          "TaskEnabled": true,
          "IsClientOnly": true
        },
        {
          "$type": "RPG.GameCore.WaitAnimState",
          "TargetType": {
            "$type": "RPG.GameCore.TargetAlias",
            "Alias": "Caster"
          },
          "AnimStateName": "Attack",
          "NormalizedTimeEnd": {
            "FixedValue": {
              "RawValue": 1455993912,
              "Value": 0.34
            }
          },
          "TaskEnabled": true,
          "IsClientOnly": true
        },
        {
          "$type": "RPG.GameCore.RemoveEffect",
          "TargetType": {
            "$type": "RPG.GameCore.TargetAlias",
            "Alias": "Caster"
          },
          "EffectPath": "Effects/Eff_Prefab/Eff_Monster/Eff_W2_Beast02_01/Eff_Monster_W2_Beast02_01_MazeSkill01_Bullet_01_Lod0.prefab",
          "FadeOutRegionStart": -1.0,
          "FadeOutRegionEnd": -1.0,
          "TaskEnabled": true,
          "IsClientOnly": true
        },
        {
          "$type": "RPG.GameCore.AdventureFireProjectile",
          "TargetType": {
            "$type": "RPG.GameCore.TargetAlias",
            "Alias": "AbilityTargetEntity"
          },
          "Projectile": {
            "ColliderTemplate": "CapsuleZ_MazeMonsterLaserBullet",
            "Behavior": "LinearWithHitDetect",
            "FlySpeed": 20.0,
            "EnableRayCast": true,
            "FlyTime": -1.0,
            "MaxLifeTime": 1.0,
            "AttachPoint": "Eff_HandL",
            "AlignWithAttachPoint": true,
            "AttachPointAxis": "Y",
            "TargetAttachPoint": "Root",
            "FlyEffect": "Effects/Eff_Prefab/Eff_Monster/Eff_W2_Beast02_01/Eff_Monster_W2_Beast02_01_MazeSkill01_Bullet_01_Lod0.prefab",
            "HitEffect": "Effects/Eff_Prefab/Eff_Monster/Eff_W2_Beast02_01/Eff_Monster_W2_Beast02_01_Maze_Hit_Lod0.prefab",
            "LinearPitchAngle": {},
            "BoomerangEccentricity": 1.0,
            "TriggerHitCallback": true,
            "StaticProjectileCanPassAirWall": true,
            "ParabolaUseWorldSpaceUp": true,
            "SubCurveIndex": {}
          },
          "OnProjectileHit": [
            {
              "$type": "RPG.GameCore.AdventureTriggerAttack",
              "AttackTargetType": {
                "$type": "RPG.GameCore.TargetAlias",
                "Alias": "ProjectileHitEntity"
              },
              "AttackRootTargetType": {
                "$type": "RPG.GameCore.TargetAlias",
                "Alias": "ProjectileHitEntity"
              },
              "TriggerBattle": true,
              "TriggerBattleDelay": 0.1,
              "AttackDetectConfig": {
                "$type": "RPG.GameCore.AdventureAttackDetectCircleConfig",
                "MaxRadius": 0.1,
                "FanAngle": 360.0,
                "Hight": 1.0
              },
              "HitConfig": {
                "HitAnimation": "Hit"
              },
              "IncludeProps": true,
              "AttackDetectCollision": true,
              "TaskEnabled": true,
              "IsClientOnly": true
            }
          ],
          "OnProjectileLifetimeFinish": [
            {
              "$type": "RPG.GameCore.AdventureTriggerAttack",
              "AttackTargetType": {
                "$type": "RPG.GameCore.TargetAlias",
                "Alias": "ProjectileHitEntity"
              },
              "AttackRootTargetType": {
                "$type": "RPG.GameCore.TargetAlias",
                "Alias": "ProjectileHitEntity"
              },
              "TriggerBattle": true,
              "TriggerBattleDelay": 0.1,
              "AttackDetectConfig": {
                "$type": "RPG.GameCore.AdventureAttackDetectCircleConfig",
                "MaxRadius": 0.1,
                "FanAngle": 360.0,
                "Hight": 1.0
              },
              "HitConfig": {
                "HitAnimation": "Hit",
                "HitSoundEvent": "Ev_sfx_monster_skill_01_hit_fireelite"
              },
              "IncludeProps": true,
              "AttackDetectCollision": true,
              "TaskEnabled": true,
              "IsClientOnly": true
            }
          ],
          "TaskEnabled": true,
          "IsClientOnly": true
        },
        {
          "$type": "RPG.GameCore.VCameraConfigChange",
          "CameraConfig": {
            "ShakeTemplateName": "Impact_Middle"
          },
          "TaskEnabled": true,
          "IsClientOnly": true
        },
        {
          "$type": "RPG.GameCore.WaitAnimState",
          "TargetType": {
            "$type": "RPG.GameCore.TargetAlias",
            "Alias": "Caster"
          },
          "AnimStateName": "Attack",
          "NormalizedTimeEnd": {
            "FixedValue": {
              "RawValue": 4294967296,
              "Value": 1.0
            }
          },
          "TaskEnabled": true,
          "IsClientOnly": true
        }
      ]
    },
    {
      "Name": "MazeMonster_W2_Best02_01_EnhanceEffect",
      "TargetInfo": {
        "TargetType": "Caster"
      },
      "OnStart": [
        {
          "$type": "RPG.GameCore.TriggerEffect",
          "TargetType": {
            "$type": "RPG.GameCore.TargetAlias",
            "Alias": "Caster"
          },
          "EffectPath": "Effects/Eff_Prefab/Eff_Common/Eff_Common_Rogue_EliteEnhance.prefab",
          "AttachPoint": "Origin",
          "PositionOffset": {
            "y": -0.2,
            "z": 0.6,
            "normalized": {
              "y": -0.316227764,
              "z": 0.9486833,
              "magnitude": 1.0,
              "sqrMagnitude": 1.0
            },
            "magnitude": 0.6324555,
            "sqrMagnitude": 0.4
          },
          "Scale": {
            "x": -1.0,
            "y": -1.0,
            "z": -1.0,
            "normalized": {
              "x": -0.577350259,
              "y": -0.577350259,
              "z": -0.577350259,
              "normalized": {
                "x": -0.5773503,
                "y": -0.5773503,
                "z": -0.5773503,
                "magnitude": 1.00000012,
                "sqrMagnitude": 1.00000024
              },
              "magnitude": 0.99999994,
              "sqrMagnitude": 0.99999994
            },
            "magnitude": 1.73205078,
            "sqrMagnitude": 3.0
          },
          "IsNeedFadeIn": true,
          "ParamEntityUsage": "LookAt",
          "TowardMaxPitchAngle": 90.0,
          "MaxMutexCount": 1,
          "TaskEnabled": true,
          "IsClientOnly": true
        }
      ]
    }
  ]
}