[
  {
    "RewardList": [
      1201001,
      1201002,
      1201003,
      1201004,
      1201005,
      1201006,
      1201007
    ],
    "GroupDesc": {
      "Hash": -1924012557,
      "Hash64": 7509559092966294882
    },
    "GroupID": 1,
    "ID": 311000
  },
  {
    "RewardList": [
      1201001,
      1201002,
      1201003,
      1201004,
      1201005,
      1201006,
      1201007
    ],
    "GroupDesc": {
      "Hash": -1924012560,
      "Hash64": 17582433578326979139
    },
    "GroupID": 2,
    "ID": 311000
  },
  {
    "RewardList": [
      1202001
    ],
    "GroupDesc": {
      "Hash": -1924012590,
      "Hash64": 2506305303945987378
    },
    "GroupID": 1,
    "ID": 311001
  },
  {
    "RewardList": [
      1202011,
      1202012,
      1202013,
      1202014,
      1202015
    ],
    "GroupDesc": {
      "Hash": -1924012591,
      "Hash64": 8880954938641585183
    },
    "GroupID": 2,
    "ID": 311001
  },
  {
    "RewardList": [
      1202011,
      1202012,
      1202013,
      1202014,
      1202015
    ],
    "GroupDesc": {
      "Hash": -1924012592,
      "Hash64": 5028585188664183632
    },
    "GroupID": 3,
    "ID": 311001
  },
  {
    "RewardList": [
      1202011,
      1202012,
      1202013,
      1202014,
      1202015
    ],
    "GroupDesc": {
      "Hash": -1924012585,
      "Hash64": 2002668869882867729
    },
    "GroupID": 4,
    "ID": 311001
  },
  {
    "RewardList": [
      1201002,
      1201003,
      1201004,
      1201005,
      1201006,
      1201007
    ],
    "GroupDesc": {
      "Hash": -337725640,
      "Hash64": 5925203082057477479
    },
    "GroupID": 1,
    "ID": 311010
  },
  {
    "RewardList": [
      1201002,
      1201003,
      1201004,
      1201005,
      1201006,
      1201007
    ],
    "GroupDesc": {
      "Hash": -337725643,
      "Hash64": 16595493658528950778
    },
    "GroupID": 2,
    "ID": 311010
  },
  {
    "RewardList": [
      1202001
    ],
    "GroupDesc": {
      "Hash": -337725673,
      "Hash64": 7414080773826580713
    },
    "GroupID": 1,
    "ID": 311011
  },
  {
    "RewardList": [
      1202012,
      1202013,
      1202014,
      1202015
    ],
    "GroupDesc": {
      "Hash": -337725674,
      "Hash64": 10798851749622074532
    },
    "GroupID": 2,
    "ID": 311011
  },
  {
    "RewardList": [
      1202012,
      1202013,
      1202014,
      1202015
    ],
    "GroupDesc": {
      "Hash": -337725675,
      "Hash64": 800193444831635349
    },
    "GroupID": 3,
    "ID": 311011
  },
  {
    "RewardList": [
      1202012,
      1202013,
      1202014,
      1202015
    ],
    "GroupDesc": {
      "Hash": -337725668,
      "Hash64": 8326630419904709292
    },
    "GroupID": 4,
    "ID": 311011
  }
]